README.md
setup.py
YJKAPI/__init__.py
YJKAPI/initializer.py
YJKAPI/DLLs/Depend/ClrYJKAPI.dll
YJKAPI/DLLs/Depend/YAPIData.dll
YJKAPI/DLLs/Depend/YJKAPI.dll
YJKAPI/DLLs/NDepend/ClrYJKAPI.dll
YJKAPI/DLLs/NDepend/DtlGeoBase.dll
YJKAPI/DLLs/NDepend/Geo.dll
YJKAPI/DLLs/NDepend/Python.Runtime.dll
YJKAPI/DLLs/NDepend/ReadDef.dll
YJKAPI/DLLs/NDepend/SPara.par
YJKAPI/DLLs/NDepend/WxlGraph64u.dll
YJKAPI/DLLs/NDepend/YAPIData.dll
YJKAPI/DLLs/NDepend/YJKAPI.dll
YJKAPI/DLLs/NDepend/YJKDesignPostUtility.dll
YJKAPI/DLLs/NDepend/YJKEditorTool.dll
YJKAPI/DLLs/NDepend/YJKExcelTool.dll
YJKAPI/DLLs/NDepend/YJKHtmlTool.dll
YJKAPI/DLLs/NDepend/YJKPdfTool.dll
YJKAPI/DLLs/NDepend/YJKWordTool.dll
YJKAPI/DLLs/NDepend/YJK_SQL.dll
YJKAPI/DLLs/NDepend/YJK_SSCS.YDB
YJKAPI/DLLs/NDepend/YJK_SSCS.dll
YJKAPI/DLLs/NDepend/dtlCmdMng.dll
YJKAPI/DLLs/NDepend/jcResultPort.dll
YJKAPI/DLLs/NDepend/jccadPort.dll
YJKAPI/DLLs/NDepend/q3dAllocMgr.dll
YJKAPI/DLLs/NDepend/q3dGeo.dll
YJKAPI/DLLs/NDepend/yjkBaseDraw.dll
YJKAPI/DLLs/NDepend/yjkCadNewData.dll
YJKAPI/DLLs/NDepend/yjkSPara.dll
YJKAPI/DLLs/NDepend/yjkTransYDB.dll
YJKAPI/DLLs/NDepend/yjksmw.dll
YJKAPI/DLLs/NDepend/ypGeo.dll
YJKAPI/YJKAPI/__init__.py
YJKAPI/_APIData/__init__.pyi
YJKAPI/_CsToYjk/__init__.pyi
YJKAPI/_DataFuncApplication/__init__.pyi
YJKAPI_TEST.egg-info/PKG-INFO
YJKAPI_TEST.egg-info/SOURCES.txt
YJKAPI_TEST.egg-info/dependency_links.txt
YJKAPI_TEST.egg-info/requires.txt
YJKAPI_TEST.egg-info/top_level.txt