Metadata-Version: 2.1
Name: YJKAPI-TEST
Version: 0.0.0.1
Summary: YJK_Python_API
Home-page: https://gitee.com/yjk-opensource/py-yjks/
Author: lme
License: UNKNOWN
Platform: UNKNOWN
Classifier: Programming Language :: Python :: 3
Classifier: License :: OSI Approved :: MIT License
Classifier: Operating System :: OS Independent
Requires-Python: >=3.7
